setup.cfg
setup.py
scikits/__init__.py
scikits.optimization.egg-info/PKG-INFO
scikits.optimization.egg-info/SOURCES.txt
scikits.optimization.egg-info/dependency_links.txt
scikits.optimization.egg-info/namespace_packages.txt
scikits.optimization.egg-info/not-zip-safe
scikits.optimization.egg-info/requires.txt
scikits.optimization.egg-info/top_level.txt
scikits/optimization/__init__.py
scikits/optimization/defaults.py
scikits/optimization/criterion/__init__.py
scikits/optimization/criterion/composite_criteria.py
scikits/optimization/criterion/criteria.py
scikits/optimization/criterion/facilities.py
scikits/optimization/criterion/information_criteria.py
scikits/optimization/criterion/tests/__init__.py
scikits/optimization/criterion/tests/test_composite_criteria.py
scikits/optimization/criterion/tests/test_criteria.py
scikits/optimization/criterion/tests/test_facilities.py
scikits/optimization/criterion/tests/test_information_criteria.py
scikits/optimization/helpers/__init__.py
scikits/optimization/helpers/finite_difference.py
scikits/optimization/helpers/levenberg_marquardt.py
scikits/optimization/helpers/quadratic.py
scikits/optimization/helpers/tests/__init__.py
scikits/optimization/helpers/tests/test_finite_difference.py
scikits/optimization/helpers/tests/test_levenberg_marquardt.py
scikits/optimization/helpers/tests/test_quadratic.py
scikits/optimization/line_search/__init__.py
scikits/optimization/line_search/adaptive_last_step_modifier.py
scikits/optimization/line_search/backtracking_search.py
scikits/optimization/line_search/barzilai_borwein_non_monotone_search.py
scikits/optimization/line_search/barzilai_borwein_search.py
scikits/optimization/line_search/cubic_interpolation.py
scikits/optimization/line_search/damped_line_search.py
scikits/optimization/line_search/fibonacci_section.py
scikits/optimization/line_search/fixed_last_step_modifier.py
scikits/optimization/line_search/golden_section.py
scikits/optimization/line_search/goldstein_rule.py
scikits/optimization/line_search/hyperbolic_line_search.py
scikits/optimization/line_search/quadratic_interpolation.py
scikits/optimization/line_search/simple_line_search.py
scikits/optimization/line_search/strong_wolfe_powell_rule.py
scikits/optimization/line_search/wolfe_powell_rule.py
