Metadata-Version: 1.0
Name: scikits.optimization
Version: 0.2
Summary: A python module for numerical optimization
Home-page: http://projects.scipy.org/scipy/scikits
Author: Matthieu Brucher
Author-email: matthieu.brucher@gmail.com
License: new BSD
Platform: UNKNOWN
Classifier: Development Status :: 4 - Beta
Classifier: Environment :: Console
Classifier: Intended Audience :: Developers
Classifier: Intended Audience :: Science/Research
Classifier: License :: OSI Approved :: BSD License
Classifier: Topic :: Scientific/Engineering
